setup.cfg
setup.py
mongofs/__init__.py
mongofs/__main__.py
mongofs/escaping.py
mongofs/json.py
mongofs/mongofs.py
mongofs/notify.py
mongofs.egg-info/PKG-INFO
mongofs.egg-info/SOURCES.txt
mongofs.egg-info/dependency_links.txt
mongofs.egg-info/entry_points.txt
mongofs.egg-info/requires.txt
mongofs.egg-info/top_level.txt