Metadata-Version: 1.1
Name: mongofs
Version: 0.1.0.2
Summary: Access Mongo documents in a FUSE filesystem
Home-page: https://github.com/paulo-raca/mongofs
Author: Paulo Costa
Author-email: me@paulo.costa.nom.br
License: UNKNOWN
Download-URL: https://github.com/paulo-raca/mongofs/0.1
Keywords: fuse,mongo
Platform: UNKNOWN
